README.rst
setup.cfg
setup.py
ftpysetup.egg-info/PKG-INFO
ftpysetup.egg-info/SOURCES.txt
ftpysetup.egg-info/dependency_links.txt
ftpysetup.egg-info/entry_points.txt
ftpysetup.egg-info/top_level.txt
ftpysetup/cmdbuild/__init__.py
ftpysetup/cmdbuild/build_rglob.py
ftpysetup/runtest/__init__.py
ftpysetup/runtest/accept.py
ftpysetup/runtest/acceptlevel.py
ftpysetup/runtest/runner.py
ftpysetup/runtest/testbase.py
ftpysetup/runtest/unit.py
ftpysetup/upvers/__init__.py
ftpysetup/upvers/upvers.py
ftpysetup/venv/__init__.py
ftpysetup/venv/venv.py
ftpysetup/website/__init__.py
ftpysetup/website/build_website.py
ftpysetup/website/website_template.py
ftpysetup/website/config/__init__.py
ftpysetup/website/example/index.rst
ftpysetup/website/example/css/default.css