Metadata-Version: 1.1
Name: ftpysetup
Version: 0.7.3
Summary: Flying Titans setuptools extensions.
Home-page: https://github.com/lanhel/ftpysetup
Author: Lance Finn Helsten
Author-email: lanhel@flyingtitans.com
License: UNKNOWN
Platform: UNKNOWN
Classifier: Development Status :: 4 - Beta
Classifier: Environment :: Console
Classifier: Framework :: Setuptools Plugin
Classifier: Intended Audience :: Developers
Classifier: License :: OSI Approved :: Apache Software License
Classifier: Operating System :: OS Independent
Classifier: Programming Language :: Python
Classifier: Topic :: Software Development :: Build Tools
